src/captcha_solver_Gottal/__init__.py
src/captcha_solver_Gottal/captcha_resolver.py
captcha_resolver_gottal-1.0.2.1.dist-info/METADATA
captcha_resolver_gottal-1.0.2.1.dist-info/WHEEL
captcha_resolver_gottal-1.0.2.1.dist-info/licenses/LICENSE
captcha_resolver_gottal-1.0.2.1.dist-info/RECORD
